kiota_bundle/__init__.py
kiota_bundle/default_request_adapter.py
microsoft_kiota_bundle-1.9.8.dist-info/METADATA
microsoft_kiota_bundle-1.9.8.dist-info/WHEEL
microsoft_kiota_bundle-1.9.8.dist-info/licenses/LICENSE
microsoft_kiota_bundle-1.9.8.dist-info/RECORD
