Metadata-Version: 2.4
Name: microsoft-kiota-bundle
Version: 1.9.8
Summary: Bundle package for kiota generated libraries in Python
License: MIT
License-File: LICENSE
Keywords: kiota,openAPI,Microsoft,Graph
Author: Microsoft
Author-email: graphtooling+python@microsoft.com
Requires-Python: >=3.9,<4.0
Classifier: Development Status :: 5 - Production/Stable
Classifier: License :: OSI Approved :: MIT License
Classifier: Programming Language :: Python :: 3
Classifier: Programming Language :: Python :: 3.9
Classifier: Programming Language :: Python :: 3.10
Classifier: Programming Language :: Python :: 3.11
Classifier: Programming Language :: Python :: 3.12
Classifier: Programming Language :: Python :: 3.13
Classifier: Programming Language :: Python :: 3.14
Requires-Dist: microsoft-kiota-abstractions (>=1.9.8,<1.10.0)
Requires-Dist: microsoft-kiota-http (>=1.9.8,<1.10.0)
Requires-Dist: microsoft-kiota-serialization-form (>=1.9.8,<1.10.0)
Requires-Dist: microsoft-kiota-serialization-json (>=1.9.8,<1.10.0)
Requires-Dist: microsoft-kiota-serialization-multipart (>=1.9.8,<1.10.0)
Requires-Dist: microsoft-kiota-serialization-text (>=1.9.8,<1.10.0)
Project-URL: Documentation, https://learn.microsoft.com/openapi/kiota/
Project-URL: Homepage, https://github.com/microsoft/kiota#readme
Project-URL: Repository, https://github.com/microsoft/kiota-python
